fhmake/__init__.py
fhmake/__main__.py
fhmake/audit.py
fhmake/build.py
fhmake/install.py
fhmake/publish.py
fhmake/utils.py
fhmake-2024.dist-info/entry_points.txt
fhmake-2024.dist-info/LICENSE.md
fhmake-2024.dist-info/METADATA
fhmake-2024.dist-info/WHEEL
fhmake-2024.dist-info/RECORD
