Metadata-Version: 2.1
Name: fhmake
Version: 2024
Summary: FredHappyface Makefile for python. build, install, publish or audit
Home-page: https://github.com/FHPythonUtils/FHMake
License: MIT
Author: FredHappyface
Requires-Python: >=3.9,<4.0
Classifier: Development Status :: 5 - Production/Stable
Classifier: Environment :: Console
Classifier: Environment :: MacOS X
Classifier: Environment :: Win32 (MS Windows)
Classifier: Intended Audience :: Developers
Classifier: Intended Audience :: Education
Classifier: License :: OSI Approved :: MIT License
Classifier: Natural Language :: English
Classifier: Operating System :: OS Independent
Classifier: Programming Language :: Python :: 3
Classifier: Programming Language :: Python :: 3.9
Classifier: Programming Language :: Python :: 3.10
Classifier: Programming Language :: Python :: 3.11
Classifier: Programming Language :: Python :: 3.12
Classifier: Programming Language :: Python :: Implementation :: CPython
Classifier: Topic :: Security
Classifier: Topic :: Software Development :: Libraries :: Python Modules
Classifier: Topic :: Utilities
Provides-Extra: full
Requires-Dist: flake8-polyfill (>=1.0.2,<2) ; extra == "full"
Requires-Dist: handsdown (>=2.1.0,<3) ; extra == "full"
Requires-Dist: licensecheck (>=2024,<2026) ; extra == "full"
Requires-Dist: poetry (>=1.7.1,<2) ; extra == "full"
Requires-Dist: pre-commit (>=3.6.0,<4) ; extra == "full"
Requires-Dist: pylint (>=3.0.3,<4) ; extra == "full"
Requires-Dist: tomlkit (>=0.12.3,<2)
Project-URL: Documentation, https://github.com/FHPythonUtils/FHMake/blob/master/README.md
Project-URL: Repository, https://github.com/FHPythonUtils/FHMake
